ghostink/__init__.py
ghostink/builtins.py
ghostink/core.py
ghostink/tests/__init__.py
ghostink/tests/test_ghostink.py
GhostInk-0.1.9.dist-info/LICENSE
GhostInk-0.1.9.dist-info/METADATA
GhostInk-0.1.9.dist-info/WHEEL
GhostInk-0.1.9.dist-info/top_level.txt
GhostInk-0.1.9.dist-info/RECORD
