Metadata-Version: 2.1
Name: GhostInk
Version: 0.1.9
Summary: A task management tool for developers.
Home-page: https://github.com/Yeeloman/GhostInk
Author: Yeeloman
Author-email: yami.onlyme@gmail.com
Keywords: task management,debugging,development tools,logging,task tracker,Python,console output,debugging tools,task organizer,development,productivity,software development
Classifier: Programming Language :: Python :: 3
Classifier: License :: OSI Approved :: MIT License
Classifier: Operating System :: OS Independent
Requires-Python: >=3.6
License-File: LICENSE
Requires-Dist: colorama
